__init__.py
ii.py
taskwarrior.py
twmodels.py
pytaskwarrior-0.4.9.dist-info/licenses/LICENSE
pytaskwarrior-0.4.9.dist-info/METADATA
pytaskwarrior-0.4.9.dist-info/WHEEL
pytaskwarrior-0.4.9.dist-info/top_level.txt
pytaskwarrior-0.4.9.dist-info/RECORD
