Metadata-Version: 2.4
Name: pytaskwarrior
Version: 0.4.9
Summary: Taskwarrior wrapper python module
Project-URL: homepage, https://github.com/sznicolas/pytaskwarrior/
Keywords: taskwarrior
Requires-Python: >=3.12
License-File: LICENSE
Requires-Dist: isodate>=0.7.2
Requires-Dist: pydantic>=2.11.7
Dynamic: license-file
